nikdev_iot/__init__.py
nikdev_iot/api/__init__.py
nikdev_iot/api/api.py
nikdev_iot/api/api_tools.py
nikdev_iot/api/exceptions.py
nikdev_iot/config/__init__.py
nikdev_iot/config/config.py
nikdev_iot/network/__init__.py
nikdev_iot/network/network.py
nikdev_iot/objects/__init__.py
nikdev_iot/objects/batch.py
nikdev_iot/objects/entry.py
nikdev_iot/objects/value.py
nikdev_iot/serializers/__init__.py
nikdev_iot/serializers/value_serializer.py
nikdev_iot-0.5.5.dist-info/LICENSE
nikdev_iot-0.5.5.dist-info/METADATA
nikdev_iot-0.5.5.dist-info/WHEEL
nikdev_iot-0.5.5.dist-info/top_level.txt
nikdev_iot-0.5.5.dist-info/RECORD
