Metadata-Version: 2.1
Name: nikdev-iot
Version: 0.5.5
Summary: Python API for NikDev IoT server.
Home-page: https://github.com/Niklasson-Development/nikdev_iot_python
Author: Johan Niklasson
Author-email: johan@nik-dev.se
License: MIT
Platform: UNKNOWN
Requires-Python: >=2.7, <4
Requires-Dist: requests (<3,>=2.19)
